contex/__init__.py
contex/client.py
contex/exceptions.py
contex/models.py
contex_python-0.1.13.dist-info/licenses/LICENSE
contex_python-0.1.13.dist-info/METADATA
contex_python-0.1.13.dist-info/WHEEL
contex_python-0.1.13.dist-info/top_level.txt
contex_python-0.1.13.dist-info/RECORD
