Metadata-Version: 2.4
Name: contex-python
Version: 0.1.13
Summary: Official Python SDK for Contex - Semantic context routing for AI agents
Author-email: Cahoots <admin@cahoots.cc>
License: MIT
Project-URL: Homepage, https://github.com/cahoots-org/contex
Project-URL: Repository, https://github.com/cahoots-org/contex
Project-URL: Issues, https://github.com/cahoots-org/contex/issues
Keywords: ai,agents,context,semantic-search,machine-learning
Classifier: Development Status :: 4 - Beta
Classifier: Intended Audience :: Developers
Classifier: License :: OSI Approved :: MIT License
Classifier: Programming Language :: Python :: 3
Classifier: Programming Language :: Python :: 3.10
Classifier: Programming Language :: Python :: 3.11
Classifier: Programming Language :: Python :: 3.12
Classifier: Topic :: Software Development :: Libraries :: Python Modules
Requires-Python: >=3.10
License-File: LICENSE
Requires-Dist: httpx>=0.25.0
Requires-Dist: pydantic>=2.0.0
Provides-Extra: dev
Requires-Dist: pytest>=7.4.0; extra == "dev"
Requires-Dist: pytest-asyncio>=0.21.0; extra == "dev"
Requires-Dist: pytest-mock>=3.12.0; extra == "dev"
Requires-Dist: black>=23.0.0; extra == "dev"
Requires-Dist: mypy>=1.5.0; extra == "dev"
Requires-Dist: ruff>=0.1.0; extra == "dev"
Dynamic: license-file
